frame_surfer/__init__.py
frame_surfer/api/__init__.py
frame_surfer/api/serializers.py
frame_surfer/api/urls.py
frame_surfer/api/views.py
frame_surfer/api_utils.py
frame_surfer/app-config-schema.json
frame_surfer/filters.py
frame_surfer/forms.py
frame_surfer/jobs/__init__.py
frame_surfer/jobs/jobs.py
frame_surfer/migrations/0001_initial.py
frame_surfer/migrations/0002_alter_frametv_name_alter_photomodel_name_and_more.py
frame_surfer/migrations/0003_alter_frametv_options.py
frame_surfer/migrations/0004_alter_photomodel_options_photomodel_thumbnail_and_more.py
frame_surfer/migrations/0005_remove_unsplashmodel_oauth_token_and_more.py
frame_surfer/migrations/0006_photomodel_tv_file_name.py
frame_surfer/migrations/__init__.py
frame_surfer/models.py
frame_surfer/navigation.py
frame_surfer/tables.py
frame_surfer/templates/frame_surfer/archive/add_api_service.html
frame_surfer/templates/frame_surfer/archive/api_service_list.html
frame_surfer/templates/frame_surfer/archive/unsplash_retrieve.html
frame_surfer/templates/frame_surfer/frametv_retrieve.html
frame_surfer/templates/frame_surfer/photomodel_list.old
frame_surfer/templates/frame_surfer/photomodel_retreive.html
frame_surfer/tests/__init__.py
frame_surfer/tests/fixtures.py
frame_surfer/tests/test_api.py
frame_surfer/tests/test_basic.py
frame_surfer/tests/test_filters.py
frame_surfer/tests/test_forms.py
frame_surfer/tests/test_models.py
frame_surfer/tests/test_views.py
frame_surfer/urls.py
frame_surfer/views.py
frame_surfer-0.1.0.dist-info/LICENSE
frame_surfer-0.1.0.dist-info/METADATA
frame_surfer-0.1.0.dist-info/WHEEL
frame_surfer-0.1.0.dist-info/RECORD
