Metadata-Version: 2.3
Name: frame-surfer
Version: 0.1.0
Summary: Frame Surfer
License: Apache-2.0
Keywords: nautobot,nautobot-app,nautobot-plugin
Author: Angelo Poggi
Author-email: angelo.poggi@networktocode.com
Requires-Python: >=3.8,<3.13
Classifier: Development Status :: 5 - Production/Stable
Classifier: Intended Audience :: Developers
Classifier: License :: OSI Approved :: Apache Software License
Classifier: Programming Language :: Python :: 3
Classifier: Programming Language :: Python :: 3.8
Classifier: Programming Language :: Python :: 3.9
Classifier: Programming Language :: Python :: 3.10
Classifier: Programming Language :: Python :: 3.11
Classifier: Programming Language :: Python :: 3.12
Provides-Extra: all
Requires-Dist: nautobot (>=2.0.0,<3.0.0)
Requires-Dist: samsungtvws (>=2.7.2,<3.0.0)
Project-URL: Documentation, https://docs.nbframesurfer.com/projects/frame-surfer/en/latest/
Project-URL: Homepage, https://github.com/angelopoggi/nautobot-app-frame-surfer
Project-URL: Repository, https://github.com/angelopoggi/nautobot-app-frame-surfer
